pymysqlwraper/__init__.py
pymysqlwraper/demo.py
pymysqlwraper/record.py
pymysqlwraper/run.py
pymysqlwraper-0.0.4.dist-info/METADATA
pymysqlwraper-0.0.4.dist-info/WHEEL
pymysqlwraper-0.0.4.dist-info/top_level.txt
pymysqlwraper-0.0.4.dist-info/RECORD
